tipsql/core/__init__.py
tipsql/core/context/__init__.py
tipsql/core/context/condition_context.py
tipsql/core/context/select_context.py
tipsql/core/dataclasses.py
tipsql/core/exception.py
tipsql/core/information_schema.py
tipsql/core/operator/eq_operator.py
tipsql/core/operator/ge_operator.py
tipsql/core/operator/gt_operator.py
tipsql/core/operator/le_operator.py
tipsql/core/operator/lt_operator.py
tipsql/core/operator/not_eq_operator.py
tipsql/core/operator/order_operator.py
tipsql/core/plugins/__init__.py
tipsql/core/plugins/database_plugin.py
tipsql/core/query/__init__.py
tipsql/core/query/builder.py
tipsql/core/query/clause/__init__.py
tipsql/core/query/clause/from_clause.py
tipsql/core/query/clause/group_by_clause.py
tipsql/core/query/clause/having_clause.py
tipsql/core/query/clause/join_clause.py
tipsql/core/query/clause/order_by_clause.py
tipsql/core/query/clause/select_columns_clause.py
tipsql/core/query/clause/where_clause.py
tipsql/core/query/clause/with_clause.py
tipsql/core/query/condition.py
tipsql/core/query/expression.py
tipsql/core/query/querable.py
tipsql/core/query/statement/__init__.py
tipsql/core/query/statement/delete.py
tipsql/core/query/statement/insert.py
tipsql/core/query/statement/select.py
tipsql/core/query/statement/update.py
tipsql/core/query/statement/with_.py
tipsql/core/relation/__init__.py
tipsql/core/relation/column.py
tipsql/core/relation/column_constraint.py
tipsql/core/relation/table.py
tipsql/core/relation/temporary_table.py
tipsql/core/relation/trait.py
tipsql/core/relation/view.py
tipsql/core/types/__init__.py
tipsql/core/types/data.py
tipsql/core/types/hint.py
tipsql/core/utils/__init__.py
tipsql/core/utils/env.py
tipsql/core/utils/jinja.py
tipsql/core/utils/rename.py
tipsql/core/value.py
tipsql_core-0.0.14.dist-info/METADATA
tipsql_core-0.0.14.dist-info/WHEEL
tipsql_core-0.0.14.dist-info/RECORD
